pybandwidth_v2/__init__.py
pybandwidth_v2/bandwidth_client.py
pybandwidth_v2/tests/__init__.py
pybandwidth_v2/tests/test_bandwidth_client.py
pybandwidth_v2-0.0.3.dist-info/LICENSE.txt
pybandwidth_v2-0.0.3.dist-info/METADATA
pybandwidth_v2-0.0.3.dist-info/WHEEL
pybandwidth_v2-0.0.3.dist-info/top_level.txt
pybandwidth_v2-0.0.3.dist-info/RECORD
